setup.py
dm/__init__.py
dm.zopepatches.fix_responsewrite_conflict.egg-info/PKG-INFO
dm.zopepatches.fix_responsewrite_conflict.egg-info/SOURCES.txt
dm.zopepatches.fix_responsewrite_conflict.egg-info/dependency_links.txt
dm.zopepatches.fix_responsewrite_conflict.egg-info/namespace_packages.txt
dm.zopepatches.fix_responsewrite_conflict.egg-info/not-zip-safe
dm.zopepatches.fix_responsewrite_conflict.egg-info/top_level.txt
dm/zopepatches/__init__.py
dm/zopepatches/fix_responsewrite_conflict/README.txt
dm/zopepatches/fix_responsewrite_conflict/VERSION.txt
dm/zopepatches/fix_responsewrite_conflict/__init__.py