Metadata-Version: 1.0
Name: dm.zopepatches.fix-responsewrite-conflict
Version: 1.0
Summary: Zope[2] patch to alleviate the effect of https://bugs.launchpad.net/zope2/+bug/740831.
Home-page: http://pypi.python.org/pypi/dm.zopepatches.fix_responsewrite_conflict
Author: Dieter Maurer
Author-email: dieter@handshake.de
License: BSD
Keywords: patch wrong response Zope2
Platform: UNKNOWN
Classifier: Development Status :: 5 - Production/Stable
Classifier: Intended Audience :: Developers
Classifier: License :: OSI Approved :: Zope Public License
Classifier: Framework :: Zope2
Classifier: Operating System :: OS Independent
Classifier: Programming Language :: Python
Classifier: Topic :: Utilities
